htvanila/__init__.py
htvanila/cli.py
htvanila/core.py
htvanila/optimizer.py
htvanila/utils.py
htvanila-0.1.1.dist-info/METADATA
htvanila-0.1.1.dist-info/WHEEL
htvanila-0.1.1.dist-info/entry_points.txt
htvanila-0.1.1.dist-info/top_level.txt
htvanila-0.1.1.dist-info/RECORD
