Metadata-Version: 2.4
Name: HtVanila
Version: 0.1.1
Summary: A library for combining HTML, CSS, JS and images into a single HTML file
Author: Developer
Author-email: acounts687@gmail.com
Classifier: Programming Language :: Python :: 3
Classifier: License :: OSI Approved :: MIT License
Classifier: Operating System :: OS Independent
Requires-Python: >=3.7
Requires-Dist: beautifulsoup4
Requires-Dist: flask
Requires-Dist: click
Requires-Dist: colorama
Requires-Dist: pillow
Dynamic: author
Dynamic: author-email
Dynamic: classifier
Dynamic: requires-dist
Dynamic: requires-python
Dynamic: summary
